gpkg.mnist-0.6.1-py2.7-nspkg.pth
gpkg/mnist/__init__.py
gpkg/mnist/cnn.py
gpkg/mnist/guild.yml
gpkg/mnist/logreg.py
gpkg/mnist/samples.py
gpkg.mnist-0.6.1.dist-info/METADATA
gpkg.mnist-0.6.1.dist-info/PACKAGE
gpkg.mnist-0.6.1.dist-info/WHEEL
gpkg.mnist-0.6.1.dist-info/entry_points.txt
gpkg.mnist-0.6.1.dist-info/namespace_packages.txt
gpkg.mnist-0.6.1.dist-info/top_level.txt
gpkg.mnist-0.6.1.dist-info/RECORD
