Metadata-Version: 2.1
Name: gpkg.mnist
Version: 0.6.1
Summary: CNN and multinomial logistic regression classifiers for MNIST digits (Guild AI)
Home-page: https://github.com/guildai/index/tree/master/gpkg/mnist
Author: Guild AI
Author-email: packages@guild.ai
License: Apache 2.0
Keywords: gpkg
Platform: UNKNOWN
